environment_kernels/__init__.py
environment_kernels/activate_helper.py
environment_kernels/core.py
environment_kernels/env_kernelspec.py
environment_kernels/envs_common.py
environment_kernels/envs_conda.py
environment_kernels/envs_virtualenv.py
environment_kernels/utils.py
environment_kernels/logos/python/logo-32x32.png
environment_kernels/logos/python/logo-64x64.png
environment_kernels/logos/r/logo-64x64.png
environment_kernels-1.2.0.dist-info/LICENSE.md
environment_kernels-1.2.0.dist-info/METADATA
environment_kernels-1.2.0.dist-info/WHEEL
environment_kernels-1.2.0.dist-info/top_level.txt
environment_kernels-1.2.0.dist-info/RECORD
